{
 "player_id":"1922",
 "name":"Briean Boddy-Calhoun",
 "position":"DB",
 "height":"5-11",
 "weight":"194",
 "current_team":"Cleveland Browns",
 "birth_date":"1993-01-21",
 "birth_place":"Wilmington, DE",
 "death_date":"None",
 "college":"Minnesota",
 "high_school":"Delcastle, DE",
 "draft_team":"None",
 "draft_round":"None",
 "draft_position":"None",
 "draft_year":"None",
 "current_salary":"540,000",
 "hof_induction_year":"None",
 "games":[
  {
   "player_id":   1922,
   "year":"2016",
   "date":"2017-01-01",
   "game_number":"16",
   "age":"23-346",
   "team":"CLE",
   "game_location":"A",
   "opponent":"PIT",
   "game_won":   false,
   "player_team_score":"24",
   "opponent_score":"27",
   "passing_attempts":   0,
   "passing_completions":   0,
   "passing_yards":   0,
   "passing_rating":   0,
   "passing_touchdowns":   0,
   "passing_interceptions":   0,
   "passing_sacks":   0,
   "passing_sacks_yards_lost":   0,
   "rushing_attempts":   0,
   "rushing_yards":   0,
   "rushing_touchdowns":   0,
   "receiving_targets":   0,
   "receiving_receptions":   0,
   "receiving_yards":   0,
   "receiving_touchdowns":   0,
   "kick_return_attempts":   0,
   "kick_return_yards":   0,
   "kick_return_touchdowns":   0,
   "punt_return_attempts":   0,
   "punt_return_yards":   0,
   "punt_return_touchdowns":   0,
   "defense_sacks":   0,
   "defense_tackles":   3,
   "defense_tackle_assists":   0,
   "defense_interceptions":{
    "propertyValue":"1",
    "annotationID":    58769
   },
   "defense_interception_yards":   67,
   "defense_interception_touchdowns":   0,
   "defense_safeties":   0,
   "point_after_attemps":   0,
   "point_after_makes":   0,
   "field_goal_attempts":   0,
   "field_goal_makes":   0,
   "punting_attempts":   0,
   "punting_yards":   0,
   "punting_blocked":   0,
   "comment":"Briean Boddy-Calhoun picked off Jones and wended his way all the way back for a touchdown, or what appeared to be a touchdown, until review showed he fumbled into the end zone and out of bounds before crossing the goal line, causing a touchback. The Steelers then went 80 yards down the field and scored on a 1.yard touchdown run by DeAngelo Williams. The Browns went from what should have been a 2.touchdown lead to a tie game. The Browns then had a chance to win the game with a minute in regulation, when Isaiah Crowell fumbled the ball away, sending the game into overtime. At this point, you wouldn't think the Browns could mess up anymore than that, but overtime brought some more miscues. Griffin moved his team down the field in the extra session, which was topped by a 43-yard completion to "
  }
 ],
 "numberGames": 1
}
